klag
