Metadata-Version: 1.1
Name: klag
Version: 1.0.2
Summary: A Kafka consumer group monitoring CLI.
Home-page: https://github.com/andrewkcarter/klag
Author: Andrew Carter
Author-email: andrew.k.carter@gmail.com
License: MIT
Keywords: kafka
Platform: UNKNOWN
Classifier: Environment :: Console
Classifier: Intended Audience :: Developers
Classifier: Intended Audience :: System Administrators
Classifier: License :: OSI Approved :: MIT License
Classifier: Topic :: System
Classifier: Topic :: System :: Distributed Computing
Classifier: Topic :: System :: Logging
Classifier: Topic :: System :: Monitoring
Classifier: Topic :: System :: Systems Administration
Classifier: Topic :: Utilities
